testapp_junguin/__init__.py
testapp_junguin/testapp_junguin.py
testapp_junguin-0.1.0.dist-info/LICENSE
testapp_junguin-0.1.0.dist-info/METADATA
testapp_junguin-0.1.0.dist-info/WHEEL
testapp_junguin-0.1.0.dist-info/RECORD
