Metadata-Version: 2.1
Name: testapp-junguin
Version: 0.1.0
Summary: UAL workshop demo
License: MIT
Author: Junguin
Requires-Python: >=3.9,<4.0
Classifier: License :: OSI Approved :: MIT License
Classifier: Programming Language :: Python :: 3
Classifier: Programming Language :: Python :: 3.9
Classifier: Programming Language :: Python :: 3.10
Classifier: Programming Language :: Python :: 3.11
Requires-Dist: pandas (>=2.0.0,<3.0.0)
